README.md
setup.py
vultr_speed/__init__.py
vultr_speed/main.py
vultr_speed.egg-info/PKG-INFO
vultr_speed.egg-info/SOURCES.txt
vultr_speed.egg-info/dependency_links.txt
vultr_speed.egg-info/entry_points.txt
vultr_speed.egg-info/requires.txt
vultr_speed.egg-info/top_level.txt